{"neighborhoods":[{"id":2827,"name":"Ahmet Efendi Mah.","southwest":{"latitude":38.519209,"longitude":27.035673},"northeast":{"latitude":38.522269,"longitude":27.041075},"geocode":{"center":{"latitude":38.5206292,"longitude":27.0391762},"area":{"polygons":[{"points":[{"latitude":"38.519209","longitude":"27.039347"},{"latitude":"38.520199","longitude":"27.041075"},{"latitude":"38.52226","longitude":"27.040439"},{"latitude":"38.522269","longitude":"27.035673"},{"latitude":"38.519209","longitude":"27.039347"}]}]}}},{"id":2828,"name":"Ahmet Taner K\u0131\u015flal\u0131 Mah.","southwest":{"latitude":38.492705,"longitude":27.077391},"northeast":{"latitude":38.498708,"longitude":27.092308},"geocode":{"center":{"latitude":38.495457,"longitude":27.084466428571},"area":{"polygons":[{"points":[{"latitude":"38.494445","longitude":"27.082479"},{"latitude":"38.492705","longitude":"27.088575"},{"latitude":"38.496611","longitude":"27.092308"},{"latitude":"38.498708","longitude":"27.087781"},{"latitude":"38.496947","longitude":"27.080252"},{"latitude":"38.494338","longitude":"27.077391"},{"latitude":"38.494445","longitude":"27.082479"}]}]}}},{"id":2837,"name":"Aosb","southwest":{"latitude":38.464667,"longitude":27.002266},"northeast":{"latitude":38.529724,"longitude":27.055423},"geocode":{"center":{"latitude":38.498447181818,"longitude":27.028860727273},"area":{"polygons":[{"points":[{"latitude":"38.521207","longitude":"27.02358"},{"latitude":"38.529724","longitude":"27.014435"},{"latitude":"38.528839","longitude":"27.002266"},{"latitude":"38.526898","longitude":"27.003068"},{"latitude":"38.494498","longitude":"27.002661"},{"latitude":"38.493218","longitude":"27.009789"},{"latitude":"38.478051","longitude":"27.009998"},{"latitude":"38.46914","longitude":"27.017613"},{"latitude":"38.471411","longitude":"27.023616"},{"latitude":"38.470021","longitude":"27.035222"},{"latitude":"38.464667","longitude":"27.0396"},{"latitude":"38.465435","longitude":"27.052384"},{"latitude":"38.472859","longitude":"27.055423"},{"latitude":"38.483432","longitude":"27.052897"},{"latitude":"38.493585","longitude":"27.047387"},{"latitude":"38.49734","longitude":"27.0454"},{"latitude":"38.503652","longitude":"27.043594"},{"latitude":"38.509042","longitude":"27.034751"},{"latitude":"38.522508","longitude":"27.03141"},{"latitude":"38.522614","longitude":"27.035234"},{"latitude":"38.52649","longitude":"27.031028"},{"latitude":"38.521207","longitude":"27.02358"}]}]}}},{"id":2833,"name":"Atat\u00fcrk Mah.","southwest":{"latitude":38.512035,"longitude":27.052442},"northeast":{"latitude":38.536739,"longitude":27.109194},"geocode":{"center":{"latitude":38.524166692308,"longitude":27.076617346154},"area":{"polygons":[{"points":[{"latitude":"38.523396","longitude":"27.056179"},{"latitude":"38.521167","longitude":"27.058721"},{"latitude":"38.516792","longitude":"27.0583"},{"latitude":"38.513745","longitude":"27.059181"},{"latitude":"38.512035","longitude":"27.063024"},{"latitude":"38.517111","longitude":"27.065343"},{"latitude":"38.518213","longitude":"27.070688"},{"latitude":"38.517336","longitude":"27.07208"},{"latitude":"38.512438","longitude":"27.070362"},{"latitude":"38.516951","longitude":"27.081606"},{"latitude":"38.522196","longitude":"27.09176"},{"latitude":"38.520386","longitude":"27.10414"},{"latitude":"38.520675","longitude":"27.104381"},{"latitude":"38.525377","longitude":"27.109194"},{"latitude":"38.536739","longitude":"27.101311"},{"latitude":"38.535391","longitude":"27.09415"},{"latitude":"38.532681","longitude":"27.093382"},{"latitude":"38.534157","longitude":"27.090631"},{"latitude":"38.530562","longitude":"27.087907"},{"latitude":"38.533925","longitude":"27.083786"},{"latitude":"38.534654","longitude":"27.07536"},{"latitude":"38.529907","longitude":"27.067329"},{"latitude":"38.526717","longitude":"27.064359"},{"latitude":"38.527176","longitude":"27.060256"},{"latitude":"38.525211","longitude":"27.052442"},{"latitude":"38.523396","longitude":"27.056179"}]}]}}},{"id":2826,"name":"Ayd\u0131nl\u0131kevler Mah.","southwest":{"latitude":38.485463,"longitude":27.074506},"northeast":{"latitude":38.494445,"longitude":27.088575},"geocode":{"center":{"latitude":38.4893255,"longitude":27.082394166667},"area":{"polygons":[{"points":[{"latitude":"38.485463","longitude":"27.080588"},{"latitude":"38.490285","longitude":"27.087629"},{"latitude":"38.492705","longitude":"27.088575"},{"latitude":"38.494445","longitude":"27.082479"},{"latitude":"38.487592","longitude":"27.074506"},{"latitude":"38.485463","longitude":"27.080588"}]}]}}},{"id":2821,"name":"Balat\u00e7\u0131k Mah.","southwest":{"latitude":38.503652,"longitude":27.03141},"northeast":{"latitude":38.522614,"longitude":27.051284},"geocode":{"center":{"latitude":38.5154729375,"longitude":27.042221375},"area":{"polygons":[{"points":[{"latitude":"38.522508","longitude":"27.03141"},{"latitude":"38.509042","longitude":"27.034751"},{"latitude":"38.503652","longitude":"27.043594"},{"latitude":"38.505311","longitude":"27.047888"},{"latitude":"38.507665","longitude":"27.048011"},{"latitude":"38.510911","longitude":"27.048365"},{"latitude":"38.512289","longitude":"27.051284"},{"latitude":"38.513437","longitude":"27.048984"},{"latitude":"38.517445","longitude":"27.048469"},{"latitude":"38.516868","longitude":"27.04525"},{"latitude":"38.52164","longitude":"27.044797"},{"latitude":"38.520199","longitude":"27.041075"},{"latitude":"38.519209","longitude":"27.039347"},{"latitude":"38.522269","longitude":"27.035673"},{"latitude":"38.522614","longitude":"27.035234"},{"latitude":"38.522508","longitude":"27.03141"}]}]}}},{"id":2811,"name":"\u00c7a\u011fda\u015f Mah.","southwest":{"latitude":38.498178,"longitude":27.05478},"northeast":{"latitude":38.508228,"longitude":27.068016},"geocode":{"center":{"latitude":38.503891,"longitude":27.06033425},"area":{"polygons":[{"points":[{"latitude":"38.503128","longitude":"27.05478"},{"latitude":"38.498178","longitude":"27.062442"},{"latitude":"38.503488","longitude":"27.067581"},{"latitude":"38.504723","longitude":"27.068016"},{"latitude":"38.503117","longitude":"27.061849"},{"latitude":"38.508228","longitude":"27.057836"},{"latitude":"38.507138","longitude":"27.05539"},{"latitude":"38.503128","longitude":"27.05478"}]}]}}},{"id":2813,"name":"Cumhuriyet Mah.","southwest":{"latitude":38.526717,"longitude":27.04941},"northeast":{"latitude":38.533849,"longitude":27.067329},"geocode":{"center":{"latitude":38.530019285714,"longitude":27.057475428571},"area":{"polygons":[{"points":[{"latitude":"38.531059","longitude":"27.05076"},{"latitude":"38.530368","longitude":"27.059454"},{"latitude":"38.527176","longitude":"27.060256"},{"latitude":"38.526717","longitude":"27.064359"},{"latitude":"38.529907","longitude":"27.067329"},{"latitude":"38.533849","longitude":"27.04941"},{"latitude":"38.531059","longitude":"27.05076"}]}]}}},{"id":2832,"name":"Egekent Mah.","southwest":{"latitude":38.503117,"longitude":27.057836},"northeast":{"latitude":38.509229,"longitude":27.069311},"geocode":{"center":{"latitude":38.506202142857,"longitude":27.063287142857},"area":{"polygons":[{"points":[{"latitude":"38.503117","longitude":"27.061849"},{"latitude":"38.504723","longitude":"27.068016"},{"latitude":"38.508526","longitude":"27.069311"},{"latitude":"38.506475","longitude":"27.063615"},{"latitude":"38.509229","longitude":"27.060534"},{"latitude":"38.508228","longitude":"27.057836"},{"latitude":"38.503117","longitude":"27.061849"}]}]}}},{"id":2831,"name":"Esentepe Mah.","southwest":{"latitude":38.505475,"longitude":27.048011},"northeast":{"latitude":38.516792,"longitude":27.063024},"geocode":{"center":{"latitude":38.509907454545,"longitude":27.055233909091},"area":{"polygons":[{"points":[{"latitude":"38.505475","longitude":"27.052824"},{"latitude":"38.507138","longitude":"27.05539"},{"latitude":"38.508228","longitude":"27.057836"},{"latitude":"38.509229","longitude":"27.060534"},{"latitude":"38.512035","longitude":"27.063024"},{"latitude":"38.513745","longitude":"27.059181"},{"latitude":"38.516792","longitude":"27.0583"},{"latitude":"38.512289","longitude":"27.051284"},{"latitude":"38.510911","longitude":"27.048365"},{"latitude":"38.507665","longitude":"27.048011"},{"latitude":"38.505475","longitude":"27.052824"}]}]}}},{"id":2830,"name":"Evka-2 Mah.","southwest":{"latitude":38.496611,"longitude":27.078112},"northeast":{"latitude":38.504769,"longitude":27.105327},"geocode":{"center":{"latitude":38.499759166667,"longitude":27.090336916667},"area":{"polygons":[{"points":[{"latitude":"38.496947","longitude":"27.080252"},{"latitude":"38.498708","longitude":"27.087781"},{"latitude":"38.496611","longitude":"27.092308"},{"latitude":"38.497836","longitude":"27.097118"},{"latitude":"38.497457","longitude":"27.105327"},{"latitude":"38.502193","longitude":"27.104051"},{"latitude":"38.504769","longitude":"27.10081"},{"latitude":"38.50176","longitude":"27.09109"},{"latitude":"38.503377","longitude":"27.085336"},{"latitude":"38.502451","longitude":"27.081606"},{"latitude":"38.498054","longitude":"27.078112"},{"latitude":"38.496947","longitude":"27.080252"}]}]}}},{"id":2834,"name":"Evka-5 Mah.","southwest":{"latitude":38.512289,"longitude":27.047669},"northeast":{"latitude":38.523396,"longitude":27.058721},"geocode":{"center":{"latitude":38.5187512,"longitude":27.0527556},"area":{"polygons":[{"points":[{"latitude":"38.52316","longitude":"27.05381"},{"latitude":"38.518079","longitude":"27.05033"},{"latitude":"38.518587","longitude":"27.047669"},{"latitude":"38.517445","longitude":"27.048469"},{"latitude":"38.513437","longitude":"27.048984"},{"latitude":"38.512289","longitude":"27.051284"},{"latitude":"38.516792","longitude":"27.0583"},{"latitude":"38.521167","longitude":"27.058721"},{"latitude":"38.523396","longitude":"27.056179"},{"latitude":"38.52316","longitude":"27.05381"}]}]}}},{"id":2829,"name":"Evka-6 Mah.","southwest":{"latitude":38.497457,"longitude":27.078697},"northeast":{"latitude":38.522196,"longitude":27.105327},"geocode":{"center":{"latitude":38.5086495,"longitude":27.09253475},"area":{"polygons":[{"points":[{"latitude":"38.505698","longitude":"27.082753"},{"latitude":"38.503377","longitude":"27.085336"},{"latitude":"38.50176","longitude":"27.09109"},{"latitude":"38.504769","longitude":"27.10081"},{"latitude":"38.502193","longitude":"27.104051"},{"latitude":"38.497457","longitude":"27.105327"},{"latitude":"38.513126","longitude":"27.102094"},{"latitude":"38.520386","longitude":"27.10414"},{"latitude":"38.522196","longitude":"27.09176"},{"latitude":"38.516951","longitude":"27.081606"},{"latitude":"38.510183","longitude":"27.078697"},{"latitude":"38.505698","longitude":"27.082753"}]}]}}},{"id":2814,"name":"G\u00fczeltepe Mah.","southwest":{"latitude":38.498018,"longitude":27.068372},"northeast":{"latitude":38.505698,"longitude":27.085336},"geocode":{"center":{"latitude":38.500641285714,"longitude":27.077599571429},"area":{"polygons":[{"points":[{"latitude":"38.498054","longitude":"27.078112"},{"latitude":"38.502451","longitude":"27.081606"},{"latitude":"38.503377","longitude":"27.085336"},{"latitude":"38.505698","longitude":"27.082753"},{"latitude":"38.498837","longitude":"27.068906"},{"latitude":"38.498018","longitude":"27.068372"},{"latitude":"38.498054","longitude":"27.078112"}]}]}}},{"id":2815,"name":"Harmandal\u0131 Gazi Mustafa Kemal Atat\u00fcrk Mah.","southwest":{"latitude":38.529907,"longitude":27.044072},"northeast":{"latitude":38.556276,"longitude":27.101311},"geocode":{"center":{"latitude":38.541082857143,"longitude":27.076082428571},"area":{"polygons":[{"points":[{"latitude":"38.533849","longitude":"27.04941"},{"latitude":"38.529907","longitude":"27.067329"},{"latitude":"38.534654","longitude":"27.07536"},{"latitude":"38.533925","longitude":"27.083786"},{"latitude":"38.530562","longitude":"27.087907"},{"latitude":"38.534157","longitude":"27.090631"},{"latitude":"38.532681","longitude":"27.093382"},{"latitude":"38.535391","longitude":"27.09415"},{"latitude":"38.536739","longitude":"27.101311"},{"latitude":"38.542619","longitude":"27.09894"},{"latitude":"38.547394","longitude":"27.101306"},{"latitude":"38.553482","longitude":"27.098982"},{"latitude":"38.550403","longitude":"27.092454"},{"latitude":"38.556276","longitude":"27.082466"},{"latitude":"38.555146","longitude":"27.073234"},{"latitude":"38.555092","longitude":"27.066961"},{"latitude":"38.546677","longitude":"27.053701"},{"latitude":"38.54255","longitude":"27.046908"},{"latitude":"38.539896","longitude":"27.046031"},{"latitude":"38.537491","longitude":"27.044072"},{"latitude":"38.533849","longitude":"27.04941"}]}]}}},{"id":2812,"name":"\u0130n\u00f6n\u00fc Mah.","southwest":{"latitude":38.525211,"longitude":27.03886},"northeast":{"latitude":38.537491,"longitude":27.060256},"geocode":{"center":{"latitude":38.530067,"longitude":27.048172111111},"area":{"polygons":[{"points":[{"latitude":"38.529506","longitude":"27.03886"},{"latitude":"38.526002","longitude":"27.040999"},{"latitude":"38.525211","longitude":"27.052442"},{"latitude":"38.527176","longitude":"27.060256"},{"latitude":"38.530553","longitude":"27.05852"},{"latitude":"38.531309","longitude":"27.05013"},{"latitude":"38.533849","longitude":"27.04941"},{"latitude":"38.537491","longitude":"27.044072"},{"latitude":"38.529506","longitude":"27.03886"}]}]}}},{"id":2824,"name":"\u0130stasyonalt\u0131 Mah.","southwest":{"latitude":38.459079,"longitude":27.047387},"northeast":{"latitude":38.494133,"longitude":27.080637},"geocode":{"center":{"latitude":38.47450626087,"longitude":27.064189391304},"area":{"polygons":[{"points":[{"latitude":"38.483432","longitude":"27.052897"},{"latitude":"38.472859","longitude":"27.055423"},{"latitude":"38.465435","longitude":"27.052384"},{"latitude":"38.462845","longitude":"27.056502"},{"latitude":"38.465372","longitude":"27.057634"},{"latitude":"38.461178","longitude":"27.056933"},{"latitude":"38.462054","longitude":"27.063432"},{"latitude":"38.459079","longitude":"27.062899"},{"latitude":"38.460204","longitude":"27.071862"},{"latitude":"38.46265","longitude":"27.071673"},{"latitude":"38.45961","longitude":"27.064818"},{"latitude":"38.462294","longitude":"27.067954"},{"latitude":"38.469376","longitude":"27.065281"},{"latitude":"38.476181","longitude":"27.067028"},{"latitude":"38.481919","longitude":"27.080637"},{"latitude":"38.482486","longitude":"27.079151"},{"latitude":"38.485463","longitude":"27.080588"},{"latitude":"38.487592","longitude":"27.074506"},{"latitude":"38.490486","longitude":"27.067617"},{"latitude":"38.491979","longitude":"27.065058"},{"latitude":"38.494133","longitude":"27.061795"},{"latitude":"38.493585","longitude":"27.047387"},{"latitude":"38.483432","longitude":"27.052897"}]}]}}},{"id":2836,"name":"\u0130zkent Mah.","southwest":{"latitude":38.506475,"longitude":27.060534},"northeast":{"latitude":38.518213,"longitude":27.07208},"geocode":{"center":{"latitude":38.511982,"longitude":27.066508},"area":{"polygons":[{"points":[{"latitude":"38.506475","longitude":"27.063615"},{"latitude":"38.508526","longitude":"27.069311"},{"latitude":"38.512438","longitude":"27.070362"},{"latitude":"38.517336","longitude":"27.07208"},{"latitude":"38.518213","longitude":"27.070688"},{"latitude":"38.517111","longitude":"27.065343"},{"latitude":"38.512035","longitude":"27.063024"},{"latitude":"38.509229","longitude":"27.060534"},{"latitude":"38.506475","longitude":"27.063615"}]}]}}},{"id":2825,"name":"Kakl\u0131\u00e7 Mah.","southwest":{"latitude":38.433694,"longitude":26.951562},"northeast":{"latitude":38.526898,"longitude":27.017613},"geocode":{"center":{"latitude":38.465162215686,"longitude":26.977361921569},"area":{"polygons":[{"points":[{"latitude":"38.445862","longitude":"26.953828"},{"latitude":"38.439092","longitude":"26.952671"},{"latitude":"38.440052","longitude":"26.954814"},{"latitude":"38.445293","longitude":"26.955438"},{"latitude":"38.443582","longitude":"26.962716"},{"latitude":"38.447556","longitude":"26.963505"},{"latitude":"38.448729","longitude":"26.967324"},{"latitude":"38.436651","longitude":"26.972345"},{"latitude":"38.436371","longitude":"26.968554"},{"latitude":"38.433694","longitude":"26.972214"},{"latitude":"38.438995","longitude":"26.975878"},{"latitude":"38.442999","longitude":"26.972115"},{"latitude":"38.447758","longitude":"26.974318"},{"latitude":"38.453501","longitude":"26.970821"},{"latitude":"38.452265","longitude":"26.974731"},{"latitude":"38.45532","longitude":"26.975419"},{"latitude":"38.449505","longitude":"26.978604"},{"latitude":"38.45348","longitude":"26.979715"},{"latitude":"38.449455","longitude":"26.984414"},{"latitude":"38.452222","longitude":"26.983772"},{"latitude":"38.454235","longitude":"26.986158"},{"latitude":"38.456154","longitude":"26.984506"},{"latitude":"38.455147","longitude":"26.988352"},{"latitude":"38.457871","longitude":"26.989435"},{"latitude":"38.451949","longitude":"26.989004"},{"latitude":"38.453688","longitude":"26.994299"},{"latitude":"38.458461","longitude":"26.995098"},{"latitude":"38.460948","longitude":"27.008581"},{"latitude":"38.468465","longitude":"27.011004"},{"latitude":"38.46914","longitude":"27.017613"},{"latitude":"38.478051","longitude":"27.009998"},{"latitude":"38.493218","longitude":"27.009789"},{"latitude":"38.494498","longitude":"27.002661"},{"latitude":"38.526898","longitude":"27.003068"},{"latitude":"38.523106","longitude":"26.989975"},{"latitude":"38.518807","longitude":"26.984322"},{"latitude":"38.514525","longitude":"26.982395"},{"latitude":"38.514409","longitude":"26.979263"},{"latitude":"38.495022","longitude":"26.979681"},{"latitude":"38.494834","longitude":"26.979898"},{"latitude":"38.487429","longitude":"26.962581"},{"latitude":"38.485501","longitude":"26.961939"},{"latitude":"38.486026","longitude":"26.966814"},{"latitude":"38.482324","longitude":"26.970265"},{"latitude":"38.478572","longitude":"26.957406"},{"latitude":"38.477796","longitude":"26.965031"},{"latitude":"38.475864","longitude":"26.96247"},{"latitude":"38.451813","longitude":"26.95912"},{"latitude":"38.449718","longitude":"26.956146"},{"latitude":"38.45056","longitude":"26.951562"},{"latitude":"38.445862","longitude":"26.953828"}]}]}}},{"id":2817,"name":"K\u00f6yi\u00e7i Mah.","southwest":{"latitude":38.491979,"longitude":27.05995},"northeast":{"latitude":38.503488,"longitude":27.069682},"geocode":{"center":{"latitude":38.497365,"longitude":27.065064555556},"area":{"polygons":[{"points":[{"latitude":"38.494133","longitude":"27.061795"},{"latitude":"38.491979","longitude":"27.065058"},{"latitude":"38.498018","longitude":"27.068372"},{"latitude":"38.498837","longitude":"27.068906"},{"latitude":"38.501356","longitude":"27.069682"},{"latitude":"38.503488","longitude":"27.067581"},{"latitude":"38.498178","longitude":"27.062442"},{"latitude":"38.496163","longitude":"27.05995"},{"latitude":"38.494133","longitude":"27.061795"}]}]}}},{"id":2835,"name":"K\u00fc\u00e7\u00fck \u00c7i\u011fli Mah.","southwest":{"latitude":38.496163,"longitude":27.043594},"northeast":{"latitude":38.507665,"longitude":27.062442},"geocode":{"center":{"latitude":38.501404,"longitude":27.051477},"area":{"polygons":[{"points":[{"latitude":"38.49734","longitude":"27.0454"},{"latitude":"38.498146","longitude":"27.048164"},{"latitude":"38.501852","longitude":"27.049603"},{"latitude":"38.496864","longitude":"27.055755"},{"latitude":"38.496163","longitude":"27.05995"},{"latitude":"38.498178","longitude":"27.062442"},{"latitude":"38.503128","longitude":"27.05478"},{"latitude":"38.507138","longitude":"27.05539"},{"latitude":"38.505475","longitude":"27.052824"},{"latitude":"38.507665","longitude":"27.048011"},{"latitude":"38.505311","longitude":"27.047888"},{"latitude":"38.503652","longitude":"27.043594"},{"latitude":"38.49734","longitude":"27.0454"}]}]}}},{"id":2818,"name":"Maltepe Mah.","southwest":{"latitude":38.487592,"longitude":27.067617},"northeast":{"latitude":38.494445,"longitude":27.082479},"geocode":{"center":{"latitude":38.4908906,"longitude":27.0752998},"area":{"polygons":[{"points":[{"latitude":"38.487592","longitude":"27.074506"},{"latitude":"38.494445","longitude":"27.082479"},{"latitude":"38.494338","longitude":"27.077391"},{"latitude":"38.490486","longitude":"27.067617"},{"latitude":"38.487592","longitude":"27.074506"}]}]}}},{"id":2820,"name":"Sasall\u0131 Merkez Mah.","southwest":{"latitude":38.490465,"longitude":26.935472},"northeast":{"latitude":38.520218,"longitude":26.979681},"geocode":{"center":{"latitude":38.507242875,"longitude":26.95323125},"area":{"polygons":[{"points":[{"latitude":"38.508845","longitude":"26.935472"},{"latitude":"38.50555","longitude":"26.939479"},{"latitude":"38.490465","longitude":"26.944953"},{"latitude":"38.495022","longitude":"26.979681"},{"latitude":"38.514409","longitude":"26.979263"},{"latitude":"38.514589","longitude":"26.963609"},{"latitude":"38.520218","longitude":"26.947921"},{"latitude":"38.508845","longitude":"26.935472"}]}]}}},{"id":2819,"name":"\u015eirintepe Mah.","southwest":{"latitude":38.490486,"longitude":27.065058},"northeast":{"latitude":38.498054,"longitude":27.080252},"geocode":{"center":{"latitude":38.494329714286,"longitude":27.072059857143},"area":{"polygons":[{"points":[{"latitude":"38.490486","longitude":"27.067617"},{"latitude":"38.494338","longitude":"27.077391"},{"latitude":"38.496947","longitude":"27.080252"},{"latitude":"38.498054","longitude":"27.078112"},{"latitude":"38.498018","longitude":"27.068372"},{"latitude":"38.491979","longitude":"27.065058"},{"latitude":"38.490486","longitude":"27.067617"}]}]}}},{"id":2822,"name":"Tuzla Mah.","southwest":{"latitude":38.428609,"longitude":26.841805},"northeast":{"latitude":38.532645,"longitude":26.979898},"geocode":{"center":{"latitude":38.48293946875,"longitude":26.92327353125},"area":{"polygons":[{"points":[{"latitude":"38.507283","longitude":"26.88501"},{"latitude":"38.503487","longitude":"26.884698"},{"latitude":"38.489921","longitude":"26.903647"},{"latitude":"38.487493","longitude":"26.903964"},{"latitude":"38.488293","longitude":"26.905961"},{"latitude":"38.483962","longitude":"26.91126"},{"latitude":"38.477526","longitude":"26.913616"},{"latitude":"38.473721","longitude":"26.917551"},{"latitude":"38.469994","longitude":"26.916955"},{"latitude":"38.471291","longitude":"26.919286"},{"latitude":"38.468325","longitude":"26.922267"},{"latitude":"38.460502","longitude":"26.923818"},{"latitude":"38.460434","longitude":"26.919917"},{"latitude":"38.460164","longitude":"26.923846"},{"latitude":"38.454989","longitude":"26.923896"},{"latitude":"38.454619","longitude":"26.931817"},{"latitude":"38.451442","longitude":"26.93799"},{"latitude":"38.44572","longitude":"26.939857"},{"latitude":"38.446216","longitude":"26.942427"},{"latitude":"38.444635","longitude":"26.942648"},{"latitude":"38.446834","longitude":"26.947053"},{"latitude":"38.443075","longitude":"26.952157"},{"latitude":"38.440825","longitude":"26.949293"},{"latitude":"38.4369","longitude":"26.951051"},{"latitude":"38.439092","longitude":"26.952671"},{"latitude":"38.445862","longitude":"26.953828"},{"latitude":"38.45056","longitude":"26.951562"},{"latitude":"38.449718","longitude":"26.956146"},{"latitude":"38.451813","longitude":"26.95912"},{"latitude":"38.475864","longitude":"26.96247"},{"latitude":"38.477796","longitude":"26.965031"},{"latitude":"38.478572","longitude":"26.957406"},{"latitude":"38.482324","longitude":"26.970265"},{"latitude":"38.486026","longitude":"26.966814"},{"latitude":"38.485501","longitude":"26.961939"},{"latitude":"38.487429","longitude":"26.962581"},{"latitude":"38.494834","longitude":"26.979898"},{"latitude":"38.495022","longitude":"26.979681"},{"latitude":"38.490465","longitude":"26.944953"},{"latitude":"38.50555","longitude":"26.939479"},{"latitude":"38.508845","longitude":"26.935472"},{"latitude":"38.520218","longitude":"26.947921"},{"latitude":"38.526115","longitude":"26.943156"},{"latitude":"38.530035","longitude":"26.925091"},{"latitude":"38.529073","longitude":"26.920981"},{"latitude":"38.531353","longitude":"26.913473"},{"latitude":"38.529608","longitude":"26.905067"},{"latitude":"38.532645","longitude":"26.898527"},{"latitude":"38.523519","longitude":"26.890999"},{"latitude":"38.51368","longitude":"26.888597"},{"latitude":"38.510348","longitude":"26.887358"},{"latitude":"38.509737","longitude":"26.880355"},{"latitude":"38.517702","longitude":"26.85594"},{"latitude":"38.520345","longitude":"26.853911"},{"latitude":"38.520113","longitude":"26.848268"},{"latitude":"38.507283","longitude":"26.88501"}]},{"points":[{"latitude":"38.52005","longitude":"26.846725"},{"latitude":"38.520113","longitude":"26.848268"},{"latitude":"38.52237","longitude":"26.841805"},{"latitude":"38.52005","longitude":"26.846725"}]},{"points":[{"latitude":"38.428609","longitude":"26.944924"},{"latitude":"38.436727","longitude":"26.951129"},{"latitude":"38.4369","longitude":"26.951051"},{"latitude":"38.428609","longitude":"26.944924"}]}]}}},{"id":2838,"name":"U\u011fur Mumcu Mah.","southwest":{"latitude":38.516868,"longitude":27.040439},"northeast":{"latitude":38.526002,"longitude":27.056179},"geocode":{"center":{"latitude":38.521087166667,"longitude":27.046877833333},"area":{"polygons":[{"points":[{"latitude":"38.520199","longitude":"27.041075"},{"latitude":"38.52164","longitude":"27.044797"},{"latitude":"38.516868","longitude":"27.04525"},{"latitude":"38.517445","longitude":"27.048469"},{"latitude":"38.518587","longitude":"27.047669"},{"latitude":"38.518079","longitude":"27.05033"},{"latitude":"38.52316","longitude":"27.05381"},{"latitude":"38.523396","longitude":"27.056179"},{"latitude":"38.525211","longitude":"27.052442"},{"latitude":"38.526002","longitude":"27.040999"},{"latitude":"38.52226","longitude":"27.040439"},{"latitude":"38.520199","longitude":"27.041075"}]}]}}},{"id":2816,"name":"Yakakent Mah.","southwest":{"latitude":38.498837,"longitude":27.067581},"northeast":{"latitude":38.516951,"longitude":27.082753},"geocode":{"center":{"latitude":38.5063556,"longitude":27.0726596},"area":{"polygons":[{"points":[{"latitude":"38.501356","longitude":"27.069682"},{"latitude":"38.498837","longitude":"27.068906"},{"latitude":"38.505698","longitude":"27.082753"},{"latitude":"38.510183","longitude":"27.078697"},{"latitude":"38.516951","longitude":"27.081606"},{"latitude":"38.512438","longitude":"27.070362"},{"latitude":"38.508526","longitude":"27.069311"},{"latitude":"38.504723","longitude":"27.068016"},{"latitude":"38.503488","longitude":"27.067581"},{"latitude":"38.501356","longitude":"27.069682"}]}]}}},{"id":2823,"name":"Yeni Mahalle Mah.","southwest":{"latitude":38.493585,"longitude":27.0454},"northeast":{"latitude":38.501852,"longitude":27.061795},"geocode":{"center":{"latitude":38.4964585,"longitude":27.051930125},"area":{"polygons":[{"points":[{"latitude":"38.493585","longitude":"27.047387"},{"latitude":"38.494133","longitude":"27.061795"},{"latitude":"38.496163","longitude":"27.05995"},{"latitude":"38.496864","longitude":"27.055755"},{"latitude":"38.501852","longitude":"27.049603"},{"latitude":"38.498146","longitude":"27.048164"},{"latitude":"38.49734","longitude":"27.0454"},{"latitude":"38.493585","longitude":"27.047387"}]}]}}}]}