{"neighborhoods":[{"id":18943,"name":"A\u00e7ma K\u00f6y\u00fc","southwest":{"latitude":40.748484,"longitude":30.991578},"northeast":{"latitude":40.765328,"longitude":31.008361},"geocode":{"center":{"latitude":40.756652666667,"longitude":30.999880166667},"area":{"polygons":[{"points":[{"latitude":"40.748484","longitude":"30.997343"},{"latitude":"40.751601","longitude":"31.003129"},{"latitude":"40.765328","longitude":"31.008361"},{"latitude":"40.76351","longitude":"31.001527"},{"latitude":"40.762509","longitude":"30.991578"},{"latitude":"40.748484","longitude":"30.997343"}]}]}}},{"id":18952,"name":"A\u00e7ma Mah.","southwest":{"latitude":40.762509,"longitude":30.975735},"northeast":{"latitude":40.774902,"longitude":31.002215},"geocode":{"center":{"latitude":40.769924,"longitude":30.989137909091},"area":{"polygons":[{"points":[{"latitude":"40.769201","longitude":"30.976132"},{"latitude":"40.76614","longitude":"30.979653"},{"latitude":"40.762509","longitude":"30.991578"},{"latitude":"40.76351","longitude":"31.001527"},{"latitude":"40.76903","longitude":"31.002215"},{"latitude":"40.774766","longitude":"31.000127"},{"latitude":"40.774902","longitude":"30.997984"},{"latitude":"40.774449","longitude":"30.992149"},{"latitude":"40.772051","longitude":"30.987285"},{"latitude":"40.773405","longitude":"30.975735"},{"latitude":"40.769201","longitude":"30.976132"}]}]}}},{"id":18942,"name":"Aksu K\u00f6y\u00fc","southwest":{"latitude":40.743266,"longitude":30.949954},"northeast":{"latitude":40.770365,"longitude":30.972607},"geocode":{"center":{"latitude":40.755026111111,"longitude":30.961261111111},"area":{"polygons":[{"points":[{"latitude":"40.748233","longitude":"30.951258"},{"latitude":"40.743266","longitude":"30.96697"},{"latitude":"40.744933","longitude":"30.968516"},{"latitude":"40.749122","longitude":"30.9724"},{"latitude":"40.767517","longitude":"30.972607"},{"latitude":"40.770365","longitude":"30.967403"},{"latitude":"40.765649","longitude":"30.950984"},{"latitude":"40.757917","longitude":"30.949954"},{"latitude":"40.748233","longitude":"30.951258"}]}]}}},{"id":18946,"name":"Bakacak K\u00f6y\u00fc","southwest":{"latitude":40.66728,"longitude":30.968516},"northeast":{"latitude":40.749122,"longitude":31.001622},"geocode":{"center":{"latitude":40.71595525,"longitude":30.981762},"area":{"polygons":[{"points":[{"latitude":"40.740115","longitude":"30.971937"},{"latitude":"40.726407","longitude":"30.974465"},{"latitude":"40.722542","longitude":"30.96862"},{"latitude":"40.66728","longitude":"30.973019"},{"latitude":"40.677508","longitude":"30.989252"},{"latitude":"40.678148","longitude":"30.994615"},{"latitude":"40.677577","longitude":"30.998571"},{"latitude":"40.721376","longitude":"31.001622"},{"latitude":"40.74634","longitude":"30.99619"},{"latitude":"40.749122","longitude":"30.9724"},{"latitude":"40.744933","longitude":"30.968516"},{"latitude":"40.740115","longitude":"30.971937"}]}]}}},{"id":18958,"name":"Bekiro\u011flu K\u00f6y\u00fc","southwest":{"latitude":40.719458,"longitude":30.901622},"northeast":{"latitude":40.768116,"longitude":30.92676},"geocode":{"center":{"latitude":40.738941777778,"longitude":30.915254777778},"area":{"polygons":[{"points":[{"latitude":"40.721843","longitude":"30.910896"},{"latitude":"40.719697","longitude":"30.911836"},{"latitude":"40.719458","longitude":"30.91397"},{"latitude":"40.731234","longitude":"30.92171"},{"latitude":"40.74181","longitude":"30.923612"},{"latitude":"40.759318","longitude":"30.92676"},{"latitude":"40.767157","longitude":"30.915991"},{"latitude":"40.768116","longitude":"30.901622"},{"latitude":"40.721843","longitude":"30.910896"}]}]}}},{"id":18944,"name":"Bekiro\u011flu K\u00f6y\u00fc (Kum Mah.)","southwest":{"latitude":40.75889,"longitude":30.897063},"northeast":{"latitude":40.79309,"longitude":30.936036},"geocode":{"center":{"latitude":40.772079111111,"longitude":30.917203333333},"area":{"polygons":[{"points":[{"latitude":"40.768116","longitude":"30.901622"},{"latitude":"40.767157","longitude":"30.915991"},{"latitude":"40.759318","longitude":"30.92676"},{"latitude":"40.75889","longitude":"30.933842"},{"latitude":"40.770668","longitude":"30.936036"},{"latitude":"40.772489","longitude":"30.926626"},{"latitude":"40.79309","longitude":"30.915268"},{"latitude":"40.790868","longitude":"30.897063"},{"latitude":"40.768116","longitude":"30.901622"}]}]}}},{"id":18961,"name":"\u00c7aml\u0131bel K\u00f6y\u00fc","southwest":{"latitude":40.67565,"longitude":30.998571},"northeast":{"latitude":40.747955,"longitude":31.034735},"geocode":{"center":{"latitude":40.716044222222,"longitude":31.017123888889},"area":{"polygons":[{"points":[{"latitude":"40.67565","longitude":"31.004847"},{"latitude":"40.732185","longitude":"31.033025"},{"latitude":"40.735616","longitude":"31.034735"},{"latitude":"40.73808","longitude":"31.032833"},{"latitude":"40.747955","longitude":"31.02521"},{"latitude":"40.740309","longitude":"31.018425"},{"latitude":"40.721376","longitude":"31.001622"},{"latitude":"40.677577","longitude":"30.998571"},{"latitude":"40.67565","longitude":"31.004847"}]}]}}},{"id":18939,"name":"\u00c7aml\u0131bel K\u00f6y\u00fc (Dere Mah.)","southwest":{"latitude":40.740309,"longitude":31.01487},"northeast":{"latitude":40.752305,"longitude":31.02521},"geocode":{"center":{"latitude":40.7465726,"longitude":31.0203164},"area":{"polygons":[{"points":[{"latitude":"40.740309","longitude":"31.018425"},{"latitude":"40.747955","longitude":"31.02521"},{"latitude":"40.752305","longitude":"31.024652"},{"latitude":"40.751985","longitude":"31.01487"},{"latitude":"40.740309","longitude":"31.018425"}]}]}}},{"id":18945,"name":"\u00c7aml\u0131bel K\u00f6y\u00fc (Karaca Mah.)","southwest":{"latitude":40.729984,"longitude":31.032833},"northeast":{"latitude":40.743549,"longitude":31.066533},"geocode":{"center":{"latitude":40.7362163,"longitude":31.0455789},"area":{"polygons":[{"points":[{"latitude":"40.735616","longitude":"31.034735"},{"latitude":"40.732185","longitude":"31.033025"},{"latitude":"40.729984","longitude":"31.037244"},{"latitude":"40.730585","longitude":"31.045743"},{"latitude":"40.735114","longitude":"31.066533"},{"latitude":"40.738127","longitude":"31.065189"},{"latitude":"40.743307","longitude":"31.0631"},{"latitude":"40.743549","longitude":"31.042652"},{"latitude":"40.73808","longitude":"31.032833"},{"latitude":"40.735616","longitude":"31.034735"}]}]}}},{"id":18938,"name":"\u00c7ay K\u00f6y\u00fc K\u00f6y\u00fc","southwest":{"latitude":40.74181,"longitude":30.923612},"northeast":{"latitude":40.759318,"longitude":30.951258},"geocode":{"center":{"latitude":40.749450444444,"longitude":30.938748888889},"area":{"polygons":[{"points":[{"latitude":"40.744998","longitude":"30.936983"},{"latitude":"40.741851","longitude":"30.940165"},{"latitude":"40.747039","longitude":"30.949183"},{"latitude":"40.748233","longitude":"30.951258"},{"latitude":"40.757917","longitude":"30.949954"},{"latitude":"40.75889","longitude":"30.933842"},{"latitude":"40.759318","longitude":"30.92676"},{"latitude":"40.74181","longitude":"30.923612"},{"latitude":"40.744998","longitude":"30.936983"}]}]}}},{"id":18941,"name":"De\u011firmentepe K\u00f6y\u00fc","southwest":{"latitude":40.719697,"longitude":30.834926},"northeast":{"latitude":40.786532,"longitude":30.911836},"geocode":{"center":{"latitude":40.753413615385,"longitude":30.861024384615},"area":{"polygons":[{"points":[{"latitude":"40.763117","longitude":"30.836251"},{"latitude":"40.75795","longitude":"30.838595"},{"latitude":"40.755501","longitude":"30.840944"},{"latitude":"40.752087","longitude":"30.853821"},{"latitude":"40.750332","longitude":"30.861825"},{"latitude":"40.743336","longitude":"30.875074"},{"latitude":"40.725751","longitude":"30.891862"},{"latitude":"40.719697","longitude":"30.911836"},{"latitude":"40.721843","longitude":"30.910896"},{"latitude":"40.786532","longitude":"30.860485"},{"latitude":"40.782881","longitude":"30.840551"},{"latitude":"40.772233","longitude":"30.834926"},{"latitude":"40.763117","longitude":"30.836251"}]}]}}},{"id":18955,"name":"Esen Mah.","southwest":{"latitude":40.780682,"longitude":30.999378},"northeast":{"latitude":40.80399,"longitude":31.029294},"geocode":{"center":{"latitude":40.793402666667,"longitude":31.010493666667},"area":{"polygons":[{"points":[{"latitude":"40.796689","longitude":"31.003638"},{"latitude":"40.795359","longitude":"31.000319"},{"latitude":"40.78457","longitude":"31.003829"},{"latitude":"40.780682","longitude":"31.007596"},{"latitude":"40.78668","longitude":"31.029294"},{"latitude":"40.795715","longitude":"31.022187"},{"latitude":"40.80025","longitude":"31.024564"},{"latitude":"40.80399","longitude":"30.999378"},{"latitude":"40.796689","longitude":"31.003638"}]}]}}},{"id":18947,"name":"Fatih Mah.","southwest":{"latitude":40.76351,"longitude":31.000127},"northeast":{"latitude":40.78668,"longitude":31.030394},"geocode":{"center":{"latitude":40.7740865,"longitude":31.009566},"area":{"polygons":[{"points":[{"latitude":"40.76903","longitude":"31.002215"},{"latitude":"40.76351","longitude":"31.001527"},{"latitude":"40.765328","longitude":"31.008361"},{"latitude":"40.770233","longitude":"31.010727"},{"latitude":"40.781201","longitude":"31.030394"},{"latitude":"40.78668","longitude":"31.029294"},{"latitude":"40.780682","longitude":"31.007596"},{"latitude":"40.780405","longitude":"31.003204"},{"latitude":"40.774766","longitude":"31.000127"},{"latitude":"40.76903","longitude":"31.002215"}]}]}}},{"id":18940,"name":"G\u00fczeldere K\u00f6y\u00fc","southwest":{"latitude":40.67565,"longitude":31.004847},"northeast":{"latitude":40.735114,"longitude":31.068439},"geocode":{"center":{"latitude":40.710528066667,"longitude":31.0482798},"area":{"polygons":[{"points":[{"latitude":"40.689234","longitude":"31.051043"},{"latitude":"40.69235","longitude":"31.064969"},{"latitude":"40.700045","longitude":"31.068439"},{"latitude":"40.709939","longitude":"31.068434"},{"latitude":"40.706547","longitude":"31.059909"},{"latitude":"40.706762","longitude":"31.037759"},{"latitude":"40.710754","longitude":"31.031191"},{"latitude":"40.721013","longitude":"31.035827"},{"latitude":"40.728525","longitude":"31.068191"},{"latitude":"40.735114","longitude":"31.066533"},{"latitude":"40.730585","longitude":"31.045743"},{"latitude":"40.729984","longitude":"31.037244"},{"latitude":"40.732185","longitude":"31.033025"},{"latitude":"40.67565","longitude":"31.004847"},{"latitude":"40.689234","longitude":"31.051043"}]}]}}},{"id":18962,"name":"G\u00fczeldere K\u00f6y\u00fc (Deli Mehmet Mah.)","southwest":{"latitude":40.706547,"longitude":31.031191},"northeast":{"latitude":40.728525,"longitude":31.068434},"geocode":{"center":{"latitude":40.714936142857,"longitude":31.048162571429},"area":{"polygons":[{"points":[{"latitude":"40.721013","longitude":"31.035827"},{"latitude":"40.710754","longitude":"31.031191"},{"latitude":"40.706762","longitude":"31.037759"},{"latitude":"40.706547","longitude":"31.059909"},{"latitude":"40.709939","longitude":"31.068434"},{"latitude":"40.728525","longitude":"31.068191"},{"latitude":"40.721013","longitude":"31.035827"}]}]}}},{"id":18935,"name":"Hac\u0131s\u00fcleymanbey K\u00f6y\u00fc","southwest":{"latitude":40.757917,"longitude":30.933842},"northeast":{"latitude":40.770668,"longitude":30.950984},"geocode":{"center":{"latitude":40.76323,"longitude":30.944806833333},"area":{"polygons":[{"points":[{"latitude":"40.757917","longitude":"30.949954"},{"latitude":"40.765649","longitude":"30.950984"},{"latitude":"40.768339","longitude":"30.948071"},{"latitude":"40.770668","longitude":"30.936036"},{"latitude":"40.75889","longitude":"30.933842"},{"latitude":"40.757917","longitude":"30.949954"}]}]}}},{"id":18936,"name":"Hac\u0131yakup K\u00f6y\u00fc","southwest":{"latitude":40.751601,"longitude":31.003129},"northeast":{"latitude":40.781201,"longitude":31.036667},"geocode":{"center":{"latitude":40.762779375,"longitude":31.01795875},"area":{"polygons":[{"points":[{"latitude":"40.751985","longitude":"31.01487"},{"latitude":"40.752305","longitude":"31.024652"},{"latitude":"40.777597","longitude":"31.036667"},{"latitude":"40.781201","longitude":"31.030394"},{"latitude":"40.770233","longitude":"31.010727"},{"latitude":"40.765328","longitude":"31.008361"},{"latitude":"40.751601","longitude":"31.003129"},{"latitude":"40.751985","longitude":"31.01487"}]}]}}},{"id":18937,"name":"Hamam\u00fcst\u00fc K\u00f6y\u00fc","southwest":{"latitude":40.73808,"longitude":31.024652},"northeast":{"latitude":40.777597,"longitude":31.064126},"geocode":{"center":{"latitude":40.754680888889,"longitude":31.043205222222},"area":{"polygons":[{"points":[{"latitude":"40.747955","longitude":"31.02521"},{"latitude":"40.73808","longitude":"31.032833"},{"latitude":"40.743549","longitude":"31.042652"},{"latitude":"40.743307","longitude":"31.0631"},{"latitude":"40.744998","longitude":"31.064126"},{"latitude":"40.750073","longitude":"31.06038"},{"latitude":"40.751656","longitude":"31.059506"},{"latitude":"40.749773","longitude":"31.05832"},{"latitude":"40.74973","longitude":"31.049048"},{"latitude":"40.754323","longitude":"31.041364"},{"latitude":"40.756126","longitude":"31.039347"},{"latitude":"40.763892","longitude":"31.042183"},{"latitude":"40.766442","longitude":"31.036907"},{"latitude":"40.771122","longitude":"31.038791"},{"latitude":"40.775373","longitude":"31.037398"},{"latitude":"40.777597","longitude":"31.036667"},{"latitude":"40.752305","longitude":"31.024652"},{"latitude":"40.747955","longitude":"31.02521"}]}]}}},{"id":18960,"name":"Hamam\u00fcst\u00fc K\u00f6y\u00fc (Cevizlik Mah.)","southwest":{"latitude":40.74973,"longitude":31.039347},"northeast":{"latitude":40.763892,"longitude":31.059506},"geocode":{"center":{"latitude":40.755984888889,"longitude":31.048095777778},"area":{"polygons":[{"points":[{"latitude":"40.756126","longitude":"31.039347"},{"latitude":"40.754323","longitude":"31.041364"},{"latitude":"40.74973","longitude":"31.049048"},{"latitude":"40.749773","longitude":"31.05832"},{"latitude":"40.751656","longitude":"31.059506"},{"latitude":"40.761136","longitude":"31.053124"},{"latitude":"40.761102","longitude":"31.050623"},{"latitude":"40.763892","longitude":"31.042183"},{"latitude":"40.756126","longitude":"31.039347"}]}]}}},{"id":18931,"name":"\u0130\u00e7meler K\u00f6y\u00fc","southwest":{"latitude":40.80025,"longitude":30.998714},"northeast":{"latitude":40.820143,"longitude":31.028896},"geocode":{"center":{"latitude":40.808940125,"longitude":31.014130875},"area":{"polygons":[{"points":[{"latitude":"40.803961","longitude":"30.998714"},{"latitude":"40.80399","longitude":"30.999378"},{"latitude":"40.80025","longitude":"31.024564"},{"latitude":"40.804625","longitude":"31.028324"},{"latitude":"40.81541","longitude":"31.028896"},{"latitude":"40.820143","longitude":"31.026948"},{"latitude":"40.819181","longitude":"31.007509"},{"latitude":"40.803961","longitude":"30.998714"}]}]}}},{"id":18949,"name":"\u0130mamlar Mah.","southwest":{"latitude":40.774766,"longitude":30.994391},"northeast":{"latitude":40.784766,"longitude":31.007596},"geocode":{"center":{"latitude":40.779284714286,"longitude":31.000730714286},"area":{"polygons":[{"points":[{"latitude":"40.774902","longitude":"30.997984"},{"latitude":"40.774766","longitude":"31.000127"},{"latitude":"40.780405","longitude":"31.003204"},{"latitude":"40.780682","longitude":"31.007596"},{"latitude":"40.78457","longitude":"31.003829"},{"latitude":"40.784766","longitude":"30.994391"},{"latitude":"40.774902","longitude":"30.997984"}]}]}}},{"id":18932,"name":"Kemeryan\u0131 K\u00f6y\u00fc","southwest":{"latitude":40.819181,"longitude":31.006501},"northeast":{"latitude":40.836039,"longitude":31.026948},"geocode":{"center":{"latitude":40.827370142857,"longitude":31.013892428571},"area":{"polygons":[{"points":[{"latitude":"40.819181","longitude":"31.007509"},{"latitude":"40.820143","longitude":"31.026948"},{"latitude":"40.82745","longitude":"31.021503"},{"latitude":"40.833731","longitude":"31.01295"},{"latitude":"40.836039","longitude":"31.014327"},{"latitude":"40.835866","longitude":"31.006501"},{"latitude":"40.819181","longitude":"31.007509"}]}]}}},{"id":18957,"name":"K\u00fclt\u00fcr Mah.","southwest":{"latitude":40.774449,"longitude":30.989375},"northeast":{"latitude":40.784766,"longitude":30.997984},"geocode":{"center":{"latitude":40.7786025,"longitude":30.9929845},"area":{"polygons":[{"points":[{"latitude":"40.778414","longitude":"30.993618"},{"latitude":"40.778293","longitude":"30.99133"},{"latitude":"40.776576","longitude":"30.991411"},{"latitude":"40.774449","longitude":"30.992149"},{"latitude":"40.774902","longitude":"30.997984"},{"latitude":"40.784766","longitude":"30.994391"},{"latitude":"40.783006","longitude":"30.989375"},{"latitude":"40.778414","longitude":"30.993618"}]}]}}},{"id":18933,"name":"Kuyud\u00fcz\u00fc Mah.","southwest":{"latitude":40.785272,"longitude":30.957619},"northeast":{"latitude":40.817729,"longitude":30.989683},"geocode":{"center":{"latitude":40.803195428571,"longitude":30.971552285714},"area":{"polygons":[{"points":[{"latitude":"40.805823","longitude":"30.964829"},{"latitude":"40.792927","longitude":"30.97244"},{"latitude":"40.785272","longitude":"30.986949"},{"latitude":"40.801269","longitude":"30.989683"},{"latitude":"40.817729","longitude":"30.964517"},{"latitude":"40.813525","longitude":"30.957619"},{"latitude":"40.805823","longitude":"30.964829"}]}]}}},{"id":18934,"name":"Muhapdede K\u00f6y\u00fc","southwest":{"latitude":40.721843,"longitude":30.860485},"northeast":{"latitude":40.790868,"longitude":30.910896},"geocode":{"center":{"latitude":40.767209285714,"longitude":30.893539142857},"area":{"polygons":[{"points":[{"latitude":"40.721843","longitude":"30.910896"},{"latitude":"40.768116","longitude":"30.901622"},{"latitude":"40.790868","longitude":"30.897063"},{"latitude":"40.790731","longitude":"30.895903"},{"latitude":"40.790532","longitude":"30.877909"},{"latitude":"40.786532","longitude":"30.860485"},{"latitude":"40.721843","longitude":"30.910896"}]}]}}},{"id":18927,"name":"Sa\u00e7mal\u0131p\u0131nar K\u00f6y\u00fc","southwest":{"latitude":40.662728,"longitude":30.929426},"northeast":{"latitude":40.747039,"longitude":30.973019},"geocode":{"center":{"latitude":40.716698789474,"longitude":30.949009736842},"area":{"polygons":[{"points":[{"latitude":"40.695883","longitude":"30.937706"},{"latitude":"40.6755","longitude":"30.937298"},{"latitude":"40.662728","longitude":"30.929426"},{"latitude":"40.66728","longitude":"30.973019"},{"latitude":"40.722542","longitude":"30.96862"},{"latitude":"40.724694","longitude":"30.962042"},{"latitude":"40.732676","longitude":"30.961141"},{"latitude":"40.732792","longitude":"30.958865"},{"latitude":"40.747039","longitude":"30.949183"},{"latitude":"40.741851","longitude":"30.940165"},{"latitude":"40.738058","longitude":"30.941353"},{"latitude":"40.734719","longitude":"30.938547"},{"latitude":"40.736688","longitude":"30.941738"},{"latitude":"40.734974","longitude":"30.949106"},{"latitude":"40.729472","longitude":"30.95515"},{"latitude":"40.720839","longitude":"30.956945"},{"latitude":"40.712143","longitude":"30.949192"},{"latitude":"40.711516","longitude":"30.943983"},{"latitude":"40.695883","longitude":"30.937706"}]}]}}},{"id":18951,"name":"Sa\u00e7mal\u0131p\u0131nar K\u00f6y\u00fc (K\u0131ran Mah.)","southwest":{"latitude":40.719458,"longitude":30.91397},"northeast":{"latitude":40.744998,"longitude":30.941353},"geocode":{"center":{"latitude":40.7330863,"longitude":30.9307617},"area":{"polygons":[{"points":[{"latitude":"40.731234","longitude":"30.92171"},{"latitude":"40.719458","longitude":"30.91397"},{"latitude":"40.720323","longitude":"30.934811"},{"latitude":"40.727178","longitude":"30.934756"},{"latitude":"40.734719","longitude":"30.938547"},{"latitude":"40.738058","longitude":"30.941353"},{"latitude":"40.741851","longitude":"30.940165"},{"latitude":"40.744998","longitude":"30.936983"},{"latitude":"40.74181","longitude":"30.923612"},{"latitude":"40.731234","longitude":"30.92171"}]}]}}},{"id":18950,"name":"Sa\u00e7mal\u0131p\u0131nar K\u00f6y\u00fc (Kurtd\u00fcz\u00fc Mah.)","southwest":{"latitude":40.732676,"longitude":30.949183},"northeast":{"latitude":40.748233,"longitude":30.96697},"geocode":{"center":{"latitude":40.739466333333,"longitude":30.957713666667},"area":{"polygons":[{"points":[{"latitude":"40.732792","longitude":"30.958865"},{"latitude":"40.732676","longitude":"30.961141"},{"latitude":"40.743266","longitude":"30.96697"},{"latitude":"40.748233","longitude":"30.951258"},{"latitude":"40.747039","longitude":"30.949183"},{"latitude":"40.732792","longitude":"30.958865"}]}]}}},{"id":18959,"name":"Sa\u00e7mal\u0131p\u0131nar K\u00f6y\u00fc (Orta Mah.)","southwest":{"latitude":40.711516,"longitude":30.934756},"northeast":{"latitude":40.736688,"longitude":30.956945},"geocode":{"center":{"latitude":40.724829181818,"longitude":30.943518636364},"area":{"polygons":[{"points":[{"latitude":"40.727178","longitude":"30.934756"},{"latitude":"40.720323","longitude":"30.934811"},{"latitude":"40.718091","longitude":"30.939721"},{"latitude":"40.711516","longitude":"30.943983"},{"latitude":"40.712143","longitude":"30.949192"},{"latitude":"40.720839","longitude":"30.956945"},{"latitude":"40.729472","longitude":"30.95515"},{"latitude":"40.734974","longitude":"30.949106"},{"latitude":"40.736688","longitude":"30.941738"},{"latitude":"40.734719","longitude":"30.938547"},{"latitude":"40.727178","longitude":"30.934756"}]}]}}},{"id":18948,"name":"Sa\u00e7mal\u0131p\u0131nar K\u00f6y\u00fc (\u015eim\u015firlitepe Mah.)","southwest":{"latitude":40.722542,"longitude":30.961141},"northeast":{"latitude":40.744933,"longitude":30.974465},"geocode":{"center":{"latitude":40.732415875,"longitude":30.966966625},"area":{"polygons":[{"points":[{"latitude":"40.724694","longitude":"30.962042"},{"latitude":"40.722542","longitude":"30.96862"},{"latitude":"40.726407","longitude":"30.974465"},{"latitude":"40.740115","longitude":"30.971937"},{"latitude":"40.744933","longitude":"30.968516"},{"latitude":"40.743266","longitude":"30.96697"},{"latitude":"40.732676","longitude":"30.961141"},{"latitude":"40.724694","longitude":"30.962042"}]}]}}},{"id":18928,"name":"Sar\u0131dere K\u00f6y\u00fc","southwest":{"latitude":40.801269,"longitude":30.964517},"northeast":{"latitude":40.835866,"longitude":31.007509},"geocode":{"center":{"latitude":40.816278375,"longitude":30.989289375},"area":{"polygons":[{"points":[{"latitude":"40.801269","longitude":"30.989683"},{"latitude":"40.803961","longitude":"30.998714"},{"latitude":"40.819181","longitude":"31.007509"},{"latitude":"40.835866","longitude":"31.006501"},{"latitude":"40.832098","longitude":"30.991345"},{"latitude":"40.818854","longitude":"30.966363"},{"latitude":"40.817729","longitude":"30.964517"},{"latitude":"40.801269","longitude":"30.989683"}]}]}}},{"id":18929,"name":"Ta\u015fl\u0131k K\u00f6y\u00fc","southwest":{"latitude":40.74634,"longitude":30.9724},"northeast":{"latitude":40.769201,"longitude":30.997343},"geocode":{"center":{"latitude":40.756956625,"longitude":30.985261625},"area":{"polygons":[{"points":[{"latitude":"40.74634","longitude":"30.99619"},{"latitude":"40.748484","longitude":"30.997343"},{"latitude":"40.762509","longitude":"30.991578"},{"latitude":"40.76614","longitude":"30.979653"},{"latitude":"40.769201","longitude":"30.976132"},{"latitude":"40.767517","longitude":"30.972607"},{"latitude":"40.749122","longitude":"30.9724"},{"latitude":"40.74634","longitude":"30.99619"}]}]}}},{"id":18956,"name":"Yaz\u0131p\u0131nar Mah.","southwest":{"latitude":40.783006,"longitude":30.986949},"northeast":{"latitude":40.80399,"longitude":31.003829},"geocode":{"center":{"latitude":40.7921888,"longitude":30.9955651},"area":{"polygons":[{"points":[{"latitude":"40.783006","longitude":"30.989375"},{"latitude":"40.784766","longitude":"30.994391"},{"latitude":"40.78457","longitude":"31.003829"},{"latitude":"40.795359","longitude":"31.000319"},{"latitude":"40.796689","longitude":"31.003638"},{"latitude":"40.80399","longitude":"30.999378"},{"latitude":"40.803961","longitude":"30.998714"},{"latitude":"40.801269","longitude":"30.989683"},{"latitude":"40.785272","longitude":"30.986949"},{"latitude":"40.783006","longitude":"30.989375"}]}]}}},{"id":18930,"name":"Yazl\u0131k K\u00f6y\u00fc","southwest":{"latitude":40.767517,"longitude":30.953267},"northeast":{"latitude":40.813525,"longitude":30.986949},"geocode":{"center":{"latitude":40.790327916667,"longitude":30.967803916667},"area":{"polygons":[{"points":[{"latitude":"40.808594","longitude":"30.95354"},{"latitude":"40.770365","longitude":"30.967403"},{"latitude":"40.767517","longitude":"30.972607"},{"latitude":"40.769201","longitude":"30.976132"},{"latitude":"40.773405","longitude":"30.975735"},{"latitude":"40.778589","longitude":"30.979586"},{"latitude":"40.785272","longitude":"30.986949"},{"latitude":"40.792927","longitude":"30.97244"},{"latitude":"40.805823","longitude":"30.964829"},{"latitude":"40.813525","longitude":"30.957619"},{"latitude":"40.810123","longitude":"30.953267"},{"latitude":"40.808594","longitude":"30.95354"}]}]}}},{"id":18953,"name":"Yeni Mah.","southwest":{"latitude":40.776576,"longitude":30.979586},"northeast":{"latitude":40.785272,"longitude":30.993618},"geocode":{"center":{"latitude":40.779532285714,"longitude":30.989097142857},"area":{"polygons":[{"points":[{"latitude":"40.776576","longitude":"30.991411"},{"latitude":"40.778293","longitude":"30.99133"},{"latitude":"40.778414","longitude":"30.993618"},{"latitude":"40.783006","longitude":"30.989375"},{"latitude":"40.785272","longitude":"30.986949"},{"latitude":"40.778589","longitude":"30.979586"},{"latitude":"40.776576","longitude":"30.991411"}]}]}}},{"id":18954,"name":"Ye\u015fil Mah.","southwest":{"latitude":40.772051,"longitude":30.975735},"northeast":{"latitude":40.778589,"longitude":30.992149},"geocode":{"center":{"latitude":40.774520166667,"longitude":30.985575166667},"area":{"polygons":[{"points":[{"latitude":"40.772051","longitude":"30.987285"},{"latitude":"40.774449","longitude":"30.992149"},{"latitude":"40.776576","longitude":"30.991411"},{"latitude":"40.778589","longitude":"30.979586"},{"latitude":"40.773405","longitude":"30.975735"},{"latitude":"40.772051","longitude":"30.987285"}]}]}}},{"id":18924,"name":"Ye\u015filova K\u00f6y\u00fc","southwest":{"latitude":40.765649,"longitude":30.948071},"northeast":{"latitude":40.808594,"longitude":30.967403},"geocode":{"center":{"latitude":40.7757192,"longitude":30.9541964},"area":{"polygons":[{"points":[{"latitude":"40.765649","longitude":"30.950984"},{"latitude":"40.770365","longitude":"30.967403"},{"latitude":"40.808594","longitude":"30.95354"},{"latitude":"40.768339","longitude":"30.948071"},{"latitude":"40.765649","longitude":"30.950984"}]}]}}},{"id":18925,"name":"Yunusefendi K\u00f6y\u00fc","southwest":{"latitude":40.721376,"longitude":30.99619},"northeast":{"latitude":40.751985,"longitude":31.018425},"geocode":{"center":{"latitude":40.740210142857,"longitude":31.004743},"area":{"polygons":[{"points":[{"latitude":"40.721376","longitude":"31.001622"},{"latitude":"40.740309","longitude":"31.018425"},{"latitude":"40.751985","longitude":"31.01487"},{"latitude":"40.751601","longitude":"31.003129"},{"latitude":"40.748484","longitude":"30.997343"},{"latitude":"40.74634","longitude":"30.99619"},{"latitude":"40.721376","longitude":"31.001622"}]}]}}},{"id":18926,"name":"Zekeriyak\u00f6y K\u00f6y\u00fc","southwest":{"latitude":40.768339,"longitude":30.915268},"northeast":{"latitude":40.810123,"longitude":30.95354},"geocode":{"center":{"latitude":40.7895261,"longitude":30.9379192},"area":{"polygons":[{"points":[{"latitude":"40.772489","longitude":"30.926626"},{"latitude":"40.770668","longitude":"30.936036"},{"latitude":"40.768339","longitude":"30.948071"},{"latitude":"40.808594","longitude":"30.95354"},{"latitude":"40.810123","longitude":"30.953267"},{"latitude":"40.803766","longitude":"30.947629"},{"latitude":"40.800423","longitude":"30.944076"},{"latitude":"40.79528","longitude":"30.928053"},{"latitude":"40.79309","longitude":"30.915268"},{"latitude":"40.772489","longitude":"30.926626"}]}]}}}]}